gryannote_audio/__init__.py
gryannote_audio/annotatedaudio.py
gryannote_audio/annotatedaudio.pyi
gryannote_audio/core.py
gryannote_audio/templates/component/__vite-browser-external-2447137e.js
gryannote_audio/templates/component/index.js
gryannote_audio/templates/component/module-2c3384e6.js
gryannote_audio/templates/component/module-aafe8b06.js
gryannote_audio/templates/component/module-d82531d9.js
gryannote_audio/templates/component/style.css
gryannote_audio/templates/component/wrapper-6f348d45-19fa94bf.js
gryannote_audio/templates/example/index.js
gryannote_audio/templates/example/style.css
gryannote_audio-0.1.6.dist-info/METADATA
gryannote_audio-0.1.6.dist-info/WHEEL
gryannote_audio-0.1.6.dist-info/RECORD
